[
  {
    "currentPrice": "0",
    "id": "67490",
    "image": "https://img.vkusvill.ru/pim/images/site_thumb/dbf75de3-dbda-414e-8bb8-a97e942947ce.png?1679400744.3779",
    "name": "Песочная корзиночка Хлебный дом Ягодное лукошко с вишней 140 г",
    "oldPrice": "0",
    "stock": 1,
    "unit": "шт",
    "url": "https://vkusvill.ru/goods/pesochnaya-korzinochka-khlebnyy-dom-yagodnoe-lukoshko-s-vishney-140-g-67490.html",
    "category": "Овощи"
  },
  {
    "currentPrice": "0",
    "id": "88740",
    "image": "https://img.vkusvill.ru/pim/images/site_thumb/73967a80-9f37-45a2-90a2-fb8affb21936.jpg?1719607847.7084",
    "name": "Печенье творожное с лимоном и курагой",
    "oldPrice": "0",
    "stock": 2,
    "unit": "шт",
    "url": "https://vkusvill.ru/goods/pechene-tvorozhnoe-s-limonom-i-kuragoy-88740.html",
    "category": "Фрукты"
  },
  {
    "currentPrice": "0",
    "id": "114546",
    "image": "https://img.vkusvill.ru/pim/images/site/site_thumb/cb3c249c-53ef-4771-9a60-fe9426e6650d.jpg",
    "name": "Кексы \"Мадлен\" в молочном шоколаде с миндалем",
    "oldPrice": "0",
    "stock": 2,
    "unit": "шт",
    "url": "https://vkusvill.ru/goods/keksy-madlen-v-molochnom-shokolade-s-mindalem-114546.html",
    "category": "Другое"
  },
  {
    "currentPrice": "0",
    "id": "16468",
    "image": "https://img.vkusvill.ru/pim/images/site_thumb/7247c95b-1bc2-4294-b3ba-fba848bbbfd2.png?1719244341.225",
    "name": "Икра форели зернистая соленая пласт/б охл., 150 г",
    "oldPrice": "0",
    "stock": null,
    "unit": "шт",
    "url": "https://vkusvill.ru/goods/ikra-foreli-zernistaya-solenaya-plast-b-okhl-150-g-16468.html",
    "category": "Морепродукты"
  },
  {
    "currentPrice": "0",
    "id": "606",
    "image": "https://img.vkusvill.ru/pim/images/site_thumb/a48e118c-f495-4893-883b-884c3ff0718d.jpg?1717795818.3529",
    "name": "Морковь",
    "oldPrice": "0",
    "stock": null,
    "unit": "шт",
    "url": "https://vkusvill.ru/goods/morkov-606.html",
    "category": "Овощи"
  },
  {
    "currentPrice": "0",
    "id": "23074",
    "image": "https://img.vkusvill.ru/pim/images/site_thumb/bd811ffd-b851-402a-9035-91bd4ee7bb08.jpg?1730869947.0926",
    "name": "Манго Египет",
    "oldPrice": "0",
    "stock": null,
    "unit": "шт",
    "url": "https://vkusvill.ru/goods/mango-egipet-23074.html",
    "category": "Фрукты"
  }
]